<?xml version="1.0" encoding="utf-8"?>
<notes>
	<note id="2565">
		<from>Obi-Wan Kenobi</from>
		<to>Luke Skywalker</to>
		<priority>High</priority>
		<heading>Reminder</heading>
		<body>Don't forget to bring pizza tonight!</body>
	</note>
	<note id="2566">
		<from>Luke Skywalker</from>
		<to>Darth Vader</to>
		<priority>Medium</priority>
		<heading>Please</heading>
		<body>I need to borrow $100!</body>
	</note>
	<note id="2567">
		<from>Luke Skywalker</from>
		<to>Leia Organa</to>
		<priority>Low</priority>
		<heading>I miss you!</heading>
	</note>
	<note id="2568">
		<from>Yoda</from>
		<to>Darth Wader</to>
		<priority>Medium</priority>
		<heading>Kill you, I will!</heading>
	</note>
</notes>